{"seeds": [{"seed": 376, "data": {"answer": "x= \\frac{3}{8}\\text{ and }-7\\text{ only}", "choices": [{"letter": "a", "value": "x=3/8\\text{ only}"}, {"letter": "b", "value": "x= \\frac{3}{8}\\text{ and }7\\text{ only}"}, {"letter": "c", "value": "x= \\frac{3}{8}\\text{ and }-7\\text{ only}"}, {"letter": "d", "value": "x=7\\text{ and }-7\\text{ only}"}, {"letter": "e", "value": "x= \\frac{3}{8}, 7\\text{, and }-7"}], "expr": "\\frac{{\\left(8 \\, x - 3\\right)} {\\left(x + 7\\right)}}{x - 7}", "__seed__": "0376"}}, {"seed": 744, "data": {"answer": "x= \\frac{-1}{1}\\text{ and }6\\text{ only}", "choices": [{"letter": "a", "value": "x=-1\\text{ only}"}, {"letter": "b", "value": "x= \\frac{-1}{1}\\text{ and }6\\text{ only}"}, {"letter": "c", "value": "x=6\\text{ and }-3\\text{ only}"}, {"letter": "d", "value": "x= \\frac{-1}{1}\\text{ and }-3\\text{ only}"}, {"letter": "e", "value": "x= \\frac{-1}{1}, 6\\text{, and }-3"}], "expr": "\\frac{{\\left(x + 1\\right)} {\\left(x - 6\\right)}}{x + 3}", "__seed__": "0744"}}, {"seed": 875, "data": {"answer": "x=-5\\text{ only}", "choices": [{"letter": "a", "value": "x= \\frac{9}{2}\\text{ and }1\\text{ only}"}, {"letter": "b", "value": "x=1\\text{ and }-5\\text{ only}"}, {"letter": "c", "value": "x= \\frac{9}{2}\\text{ and }-5\\text{ only}"}, {"letter": "d", "value": "x=-5\\text{ only}"}, {"letter": "e", "value": "x= \\frac{9}{2}, 1\\text{, and }-5"}], "expr": "\\frac{x + 5}{{\\left(2 \\, x - 9\\right)} {\\left(x - 1\\right)}}", "__seed__": "0875"}}, {"seed": 444, "data": {"answer": "x=-9\\text{ only}", "choices": [{"letter": "a", "value": "x= \\frac{-2}{1}, 3\\text{, and }-9"}, {"letter": "b", "value": "x=3\\text{ and }-9\\text{ only}"}, {"letter": "c", "value": "x= \\frac{-2}{1}\\text{ and }-9\\text{ only}"}, {"letter": "d", "value": "x=-9\\text{ only}"}, {"letter": "e", "value": "x= \\frac{-2}{1}\\text{ and }3\\text{ only}"}], "expr": "\\frac{x + 9}{{\\left(x + 2\\right)} {\\left(x - 3\\right)}}", "__seed__": "0444"}}, {"seed": 761, "data": {"answer": "x=3\\text{ only}", "choices": [{"letter": "a", "value": "x=3\\text{ only}"}, {"letter": "b", "value": "x= \\frac{-6}{5}\\text{ and }-4\\text{ only}"}, {"letter": "c", "value": "x= \\frac{-6}{5}\\text{ and }3\\text{ only}"}, {"letter": "d", "value": "x= \\frac{-6}{5}, 3\\text{, and }-4"}, {"letter": "e", "value": "x=3\\text{ and }-4\\text{ only}"}], "expr": "\\frac{x - 3}{{\\left(5 \\, x + 6\\right)} {\\left(x + 4\\right)}}", "__seed__": "0761"}}, {"seed": 727, "data": {"answer": "x=-3\\text{ only}", "choices": [{"letter": "a", "value": "x=-3\\text{ only}"}, {"letter": "b", "value": "x=6\\text{ and }-3\\text{ only}"}, {"letter": "c", "value": "x= \\frac{-5}{2}, 6\\text{, and }-3"}, {"letter": "d", "value": "x= \\frac{-5}{2}\\text{ and }6\\text{ only}"}, {"letter": "e", "value": "x= \\frac{-5}{2}\\text{ and }-3\\text{ only}"}], "expr": "\\frac{x + 3}{{\\left(2 \\, x + 5\\right)} {\\left(x - 6\\right)}}", "__seed__": "0727"}}, {"seed": 147, "data": {"answer": "x= \\frac{6}{5}\\text{ and }-5\\text{ only}", "choices": [{"letter": "a", "value": "x=6\\text{ and }-5\\text{ only}"}, {"letter": "b", "value": "x= \\frac{6}{5}, 6\\text{, and }-5"}, {"letter": "c", "value": "x= \\frac{6}{5}\\text{ and }6\\text{ only}"}, {"letter": "d", "value": "x=6/5\\text{ only}"}, {"letter": "e", "value": "x= \\frac{6}{5}\\text{ and }-5\\text{ only}"}], "expr": "\\frac{{\\left(5 \\, x - 6\\right)} {\\left(x + 5\\right)}}{x - 6}", "__seed__": "0147"}}, {"seed": 648, "data": {"answer": "x=4\\text{ only}", "choices": [{"letter": "a", "value": "x=4\\text{ only}"}, {"letter": "b", "value": "x= \\frac{-1}{2}\\text{ and }-4\\text{ only}"}, {"letter": "c", "value": "x= \\frac{-1}{2}\\text{ and }4\\text{ only}"}, {"letter": "d", "value": "x=4\\text{ and }-4\\text{ only}"}, {"letter": "e", "value": "x= \\frac{-1}{2}, 4\\text{, and }-4"}], "expr": "\\frac{x - 4}{{\\left(2 \\, x + 1\\right)} {\\left(x + 4\\right)}}", "__seed__": "0648"}}, {"seed": 859, "data": {"answer": "x= \\frac{-1}{2}\\text{ and }3\\text{ only}", "choices": [{"letter": "a", "value": "x=3\\text{ and }-3\\text{ only}"}, {"letter": "b", "value": "x=-1/2\\text{ only}"}, {"letter": "c", "value": "x= \\frac{-1}{2}, 3\\text{, and }-3"}, {"letter": "d", "value": "x= \\frac{-1}{2}\\text{ and }-3\\text{ only}"}, {"letter": "e", "value": "x= \\frac{-1}{2}\\text{ and }3\\text{ only}"}], "expr": "\\frac{{\\left(2 \\, x + 1\\right)} {\\left(x - 3\\right)}}{x + 3}", "__seed__": "0859"}}, {"seed": 398, "data": {"answer": "x=6\\text{ only}", "choices": [{"letter": "a", "value": "x= \\frac{1}{2}, 6\\text{, and }-3"}, {"letter": "b", "value": "x= \\frac{1}{2}\\text{ and }-3\\text{ only}"}, {"letter": "c", "value": "x= \\frac{1}{2}\\text{ and }6\\text{ only}"}, {"letter": "d", "value": "x=6\\text{ and }-3\\text{ only}"}, {"letter": "e", "value": "x=6\\text{ only}"}], "expr": "\\frac{x - 6}{{\\left(2 \\, x - 1\\right)} {\\left(x + 3\\right)}}", "__seed__": "0398"}}], "generated_on": "2022-07-27T13:44:19.008973+00:00"}